MANIFEST.in
README.rst
setup.py
docs/HISTORY.txt
docs/LICENSE.GPL
docs/LICENSE.txt
docs/controlpanel.png
docs/edit-config.png
ftw/__init__.py
ftw.redirector.egg-info/PKG-INFO
ftw.redirector.egg-info/SOURCES.txt
ftw.redirector.egg-info/dependency_links.txt
ftw.redirector.egg-info/entry_points.txt
ftw.redirector.egg-info/namespace_packages.txt
ftw.redirector.egg-info/not-zip-safe
ftw.redirector.egg-info/requires.txt
ftw.redirector.egg-info/top_level.txt
ftw/redirector/__init__.py
ftw/redirector/config.py
ftw/redirector/configure.zcml
ftw/redirector/excel.py
ftw/redirector/hooks.py
ftw/redirector/interfaces.py
ftw/redirector/strategy.py
ftw/redirector/testing.py
ftw/redirector/Extensions/install.py
ftw/redirector/browser/__init__.py
ftw/redirector/browser/configure.zcml
ftw/redirector/browser/excel_views.py
ftw/redirector/browser/fourohfour.py
ftw/redirector/browser/resources.zcml
ftw/redirector/browser/resources/icon.png
ftw/redirector/browser/resources/main.css
ftw/redirector/browser/resources/redirector-compiled.css
ftw/redirector/browser/resources/redirector-theming.scss
ftw/redirector/browser/resources/redirector.css
ftw/redirector/locales/ftw.redirector.pot
ftw/redirector/locales/plone.pot
ftw/redirector/locales/de/LC_MESSAGES/ftw.redirector.po
ftw/redirector/locales/de/LC_MESSAGES/plone.po
ftw/redirector/profiles/default/browserlayer.xml
ftw/redirector/profiles/default/controlpanel.xml
ftw/redirector/profiles/default/cssregistry.xml
ftw/redirector/profiles/default/metadata.xml
ftw/redirector/profiles/default/types.xml
ftw/redirector/profiles/default/types/ftw.redirector.RedirectConfig.xml
ftw/redirector/profiles/default_plone5/browserlayer.xml
ftw/redirector/profiles/default_plone5/controlpanel.xml
ftw/redirector/profiles/default_plone5/metadata.xml
ftw/redirector/profiles/default_plone5/registry.xml
ftw/redirector/profiles/default_plone5/types.xml
ftw/redirector/profiles/default_plone5/types/ftw.redirector.RedirectConfig.xml
ftw/redirector/profiles/uninstall/browserlayer.xml
ftw/redirector/profiles/uninstall/cssregistry.xml
ftw/redirector/profiles/uninstall/types.xml
ftw/redirector/profiles/uninstall_plone5/browserlayer.xml
ftw/redirector/profiles/uninstall_plone5/registry.xml
ftw/redirector/profiles/uninstall_plone5/types.xml
ftw/redirector/tests/__init__.py
